Workbook

Sheet INPUTS
B1: T=0 | C1: T+3 | D1: T+5 | E1: T+7
A2: METRIC | B2: Value(10years) | C2: Value(10+3years) | D2: Value(10+5years) | E2: Value(10+7years)
A3: Gross IRR | B3: 0.095 | C3: 0.101 | D3: 0.112 | E3: 0.123 | G3: LPs Rolling Forward | H3: 0.7
A4: Net IRR | B4: 0.072 | C4: 0.079 | D4: 0.085 | E4: 0.09 | G4: LPs Exiting | H4: 0.3
A5: TVPI(DPI+RVPI) | B5: =B6+B7 -> 1.4 | C5: =C6+C7 -> 1.56 | D5: =D6+D7 -> 1.7 | E5: =E6+E7 -> 1.86 | G5: Hurdle Rate | H5: 0.08
A6: DPI | B6: 0.5 | C6: 0.75 | D6: 1.3 | E6: 1.55 | G6: Carry Rate | H6: 0.2
A7: RVPI | B7: 0.9 | C7: 0.81 | D7: 0.4 | E7: 0.31
A8: NAV at T($M) | B8: 400 | C8: 496 | D8: 566 | E8: 622
A9: Unrealised value% | B9: 0.6429 | C9: 0.52 | D9: 0.24 | E9: 0.17
A12: Calculations
A13: Intial Capital | B13: =B5*B14 -> 622.22222 | C13: =C5*C14 -> 955.25926 | D13: =D5*D14 -> 2405.5 | E13: =E5*E14 -> 3732
A14: Paid In Capital | B14: =B8/B7 -> 444.44444 | C14: =C8/C7 -> 612.34568 | D14: =D8/D7 -> 1415 | E14: =E8/E7 -> 2006.4516
A15: Distributions | B15: =B6*B14 -> 222.22222 | C15: =C6*C14 -> 459.25926 | D15: =D6*D14 -> 1839.5 | E15: =E6*E14 -> 3110
A16: Nav | B16: =B8 -> 400 | C16: =C8 -> 496 | D16: =D8 -> 566 | E16: =E8 -> 622
A17: Unrealised Value | B17: =B8/B13 -> 0.64285714 | C17: =C8/C13 -> 0.51923077 | D17: =D8/D13 -> 0.23529412 | E17: =E8/E13 -> 0.16666667
A18: Rolling Lp Nav | B18: =$H$3*B8 -> 280 | C18: =$H$3*C8 -> 347.2 | D18: =$H$3*D8 -> 396.2 | E18: =$H$3*E8 -> 435.4
A19: Exiting Lp Nav | B19: =$H$4*B8 -> 120 | C19: =$H$4*C8 -> 148.8 | D19: =$H$4*D8 -> 169.8 | E19: =$H$4*E8 -> 186.6

Sheet RESET CARRY
A2: INPUTS | B2: Values | D2: Value Splits | E2: Value in $MN | G2: Reset Carry Calculations | J2: Final Allocation
A3: Paid in capital | B3: =INPUTS!D14 -> 1415 | D3: Rolled LPs share | E3: =B7*B6 -> 1683.85 | H3: Value in $MN | J3: Rolled LPs (after carry) | K3: =H5-H9 -> 1463.5096
A4: DPI | B4: =INPUTS!D15 -> 1839.5 | D4: Exit LPs share | E4: =B8*B6 -> 721.65 | G4: Rolled NAV baseline | H4: =B7*B5 -> 396.2 | J4: Exit LPs | K4: =E4 -> 721.65
A5: NAV | B5: =INPUTS!D16 -> 566 | G5: Rolled pool value at T+5 | H5: =E3 -> 1683.85 | J5: GP Carry | K5: =H9 -> 220.34044
A6: TVPI | B6: =INPUTS!D13 -> 2405.5 | G6: Profit | H6: =H5-H4 -> 1287.65
A7: Rolled LPs | B7: =INPUTS!H3 -> 0.7 | G7: Hurdle requirement | H7: =H4*(1+B9)^5 -> 582.14778
A8: Exit LPs | B8: =INPUTS!H4 -> 0.3 | G8: Excess above Hurdle | H8: =H5-H7 -> 1101.7022
A9: Hurdle rate | B9: =INPUTS!H5 -> 0.08 | G9: GPs Carry | H9: =B10*H8 -> 220.34044
A10: Carry | B10: =INPUTS!H6 -> 0.2

Sheet CATCHUP CARRY ONLY
A2: INPUTS | B2: Values | D2: Value Splits | E2: Value in $MN | G2: Catch up carry Model Summary
A3: Paid in capital | B3: =INPUTS!D14 -> 1415 | D3: Rolled LPs share | E3: =B7*B6 -> 1683.85 | G3: Rolled LPs | H3: =E3 -> 1683.85
A4: DPI | B4: =INPUTS!D15 -> 1839.5 | D4: Exit LPs share | E4: =B8*B6 -> 721.65 | G4: Exit Lps | H4: =E4 -> 721.65
A5: NAV | B5: =INPUTS!D16 -> 566 | G5: GP Carry | H5: 0
A6: TVPI | B6: =INPUTS!D13 -> 2405.5 | D6: Hurdle Check
A7: Rolled LPs | B7: =INPUTS!H3 -> 0.7 | D7: Fund life in yrs | E7: 15
A8: Exit LPs | B8: =INPUTS!H4 -> 0.3 | D8: Minimum Required value | E8: =B3*(1+B9)^E7 -> 4488.6193
A9: Hurdle rate | B9: =INPUTS!H5 -> 0.08 | D9: Actual value at T+5 | E9: =B6 -> 2405.5
A10: Carry | B10: =INPUTS!H6 -> 0.2 | D10: Actual(2405.5)<Required(4488.62)
A11: NET IRR | B11: =INPUTS!D4 -> 0.085 | D11: GPs Carry | E11: =0 -> 0

Sheet BLENDEDCARRY+CATCHUP+GPROLLOVER
A2: INPUTS | B2: Values | D2: Blended Carry Calculations | G2: Hurdle Check
A3: Paid in capital | B3: =INPUTS!D14 -> 1415 | E3: in $MN | G3: Hurdle requirement | H3: =E4*(1+B9)^5 -> 582.14778
A4: DPI | B4: =INPUTS!D15 -> 1839.5 | D4: Rolled NAV baseline | E4: =B7*B5 -> 396.2 | G4: Value achieved | H4: =E5 -> 1683.85
A5: NAV | B5: =INPUTS!D16 -> 566 | D5: Rolled pool value at T+5 | E5: =B7*B6 -> 1683.85 | G5: Value achieved is more than hurdle req
A6: TVPI | B6: =INPUTS!D13 -> 2405.5 | D6: Profit | E6: =E5-E4 -> 1287.65
A7: Rolled LPs | B7: =INPUTS!H3 -> 0.7 | D7: Excess above hurdle | E7: =E5-H3 -> 1101.7022 | G7: Final Allocation
A8: Exit LPs | B8: =INPUTS!H4 -> 0.3 | D8: GP Carry | E8: =B14*E7 -> 110.17022 | G8: GP total | H8: =E13 -> 174.55272
A9: Hurdle rate | B9: =INPUTS!H5 -> 0.08 | D9: GP Rollover | E9: =B15*E4 -> 19.81 | G9: Rolled LPs | H9: =E5-E8 -> 1573.6798
A10: Carry | B10: =INPUTS!H6 -> 0.2 | D10: Growth Multiple | E10: =E5/E4 -> 4.25 | G10: Exit LPs | H10: =B8*B6 -> 721.65
A11: NET IRR | B11: =INPUTS!D4 -> 0.085 | D11: Final GP Rollover value | E11: =E9*E10 -> 84.1925
D12: Profit | E12: =E11-E9 -> 64.3825
A13: Assumption | D13: GP Total profit | E13: =E8+E12 -> 174.55272
A14: Reduced Carry | B14: 0.1
A15: GP Rollover % of NAV baseline | B15: 0.05

Sheet OUTPUT
A1: MODEL | B1: Rolled LPs ($MN) | C1: Exit LPs ($MN) | D1: GP ($MN) | E1: Total ($MN)
A2: Reset Carry | B2: ='RESET CARRY'!K3 -> 1463.5096 | C2: ='RESET CARRY'!K4 -> 721.65 | D2: ='RESET CARRY'!K5 -> 220.34044 | E2: =B2+C2+D2 -> 2405.5
A3: Catchup Carry | B3: ='CATCHUP CARRY ONLY'!H3 -> 1683.85 | C3: ='CATCHUP CARRY ONLY'!H4 -> 721.65 | D3: ='CATCHUP CARRY ONLY'!H5 -> 0 | E3: =B3+C3+D3 -> 2405.5
A4: Blended + Rollover | B4: ='BLENDEDCARRY+CATCHUP+GPROLLOVER'!H9 -> 1573.6798 | C4: ='BLENDEDCARRY+CATCHUP+GPROLLOVER'!H10 -> 721.65 | D4: ='BLENDEDCARRY+CATCHUP+GPROLLOVER'!H8 -> 174.55272 | E4: =B4+C4+D4 -> 2469.8825
