Workbook

Sheet Data File
A1: Real Estate Housing Society
A2: S.No | B2: Owner | C2: Built-up Area (sq.ft.) | D2: Price per sq.ft. ($) | E2: House Price ($) | H2: S.No | I2: LP Name | J2: % Allocation | K2: Commitment (Million)
A3: 1 | B3: Kevin Hall | C3: 3953 | D3: 420.48 | E3: 1662161.1 | H3: LP1 | I3: BlackRock PE | J3: 0.12 | K3: 12000000
A4: 2 | B4: Grace Anderson | C4: 2827 | D4: 676.03 | E4: 1911142.1 | H4: LP2 | I4: CalPERS Pension Fund | J4: 0.1 | K4: 10000000
A5: 3 | B5: Lily Lee | C5: 3501 | D5: 380.61 | E5: 1332507.7 | H5: LP3 | I5: Harvard Endowment | J5: 0.08 | K5: 9000000
A6: 4 | B6: Nora Roberts | C6: 1579 | D6: 875.4 | E6: 1382253.1 | H6: LP4 | I6: Ontario Teachers | J6: 0.07 | K6: 8000000
A7: 5 | B7: Sarah Anderson | C7: 1958 | D7: 574.54 | E7: 1124942.4 | H7: LP5 | I7: GIC Singapore | J7: 0.06 | K7: 8000000
A8: 6 | B8: Michael Lee | C8: 2986 | D8: 565.47 | E8: 1688506.4 | H8: LP6 | I8: ADIA Abu Dhabi | J8: 0.07 | K8: 7000000
A9: 7 | B9: Elizabeth Moore | C9: 4906 | D9: 367.92 | E9: 1805019.6 | H9: LP7 | I9: Yale Endowment | J9: 0.05 | K9: 5000000
A10: 8 | B10: David Wilson | C10: 4804 | D10: 427.73 | E10: 2054817.9 | H10: LP8 | I10: CPP Investments | J10: 0.05 | K10: 5000000
A11: 9 | B11: Mark Rivera | C11: 2759 | D11: 416.86 | E11: 1150106 | H11: LP9 | I11: Goldman Sachs AM | J11: 0.05 | K11: 5000000
A12: 10 | B12: Christopher Wilson | C12: 2480 | D12: 574.54 | E12: 1424850.4 | H12: LP10 | I12: Temasek Holdings | J12: 0.04 | K12: 4000000
A13: 11 | B13: Aria Young | C13: 1737 | D13: 424.11 | E13: 736671.73 | H13: LP11 | I13: Fidelity PE Fund | J13: 0.04 | K13: 4000000
A14: 12 | B14: Elizabeth Adams | C14: 2486 | D14: 391.48 | E14: 973224.88 | H14: LP12 | I14: TPG Capital | J14: 0.04 | K14: 4000000
... A22: 20 | B22: Abigail Anderson | C22: 4615 | D22: 862.71 | E22: 3981410.8 | H22: LP20 | I22: Family Office (Smith Capital) | J22: 0.02 | K22: 2000000
A23: 21 | B23: James Allen | C23: 3681 | D23: 483.92 | E23: 1781293.2 | K23: =SUM(K3:K22) -> 100000000
A24: 22 | B24: Ella Garcia | C24: 4636 | D24: 891.71 | E24: 4133965.6
A25: 23 | B25: Edward Brown | C25: 2015 | D25: 897.15 | E25: 1807750.9
A26: 24 | B26: Ashley Martinez | C26: 2025 | D26: 801.09 | E26: 1622204.6
A27: 25 | B27: Kevin Hernandez | C27: 4202 | D27: 587.22 | E27: 2467512.6
A28: 26 | B28: Lily Ramirez | C28: 3446 | D28: 801.09 | E28: 2760551.6
A29: 27 | B29: Paul Jones | C29: 3751 | D29: 739.47 | E29: 2773738.8
A30: 28 | B30: Joshua Harris | C30: 2176 | D30: 538.29 | E30: 1171314.9
A31: 29 | B31: Paul Robinson | C31: 2585 | D31: 449.48 | E31: 1161904.8
A32: 30 | B32: Scarlett Taylor | C32: 3661 | D32: 451.29 | E32: 1652180.2
A33: 31 | B33: Grace Smith | C33: 3984 | D33: 761.22 | E33: 3032682.5
A34: 32 | B34: Lily Campbell | C34: 3233 | D34: 690.53 | E34: 2232487.4
A35: 33 | B35: Ashley Baker | C35: 2367 | D35: 753.97 | E35: 1784637.1
... A52: 50 | B52: Scarlett Smith | C52: 2420 | D52: 619.85 | E52: 1500029.5
B53: Total | C53: =SUM(C3:C52) -> 162861 | D53: =SUM(D3:D52) -> 30713.28 | E53: =SUM(E3:E52) -> 1e+08

Sheet Assumptions
A1: Fund
A2: Input | C2: Value
A3: Fund Size | B3: $ | C3: ='Data File'!E53 -> 1e+08
A4: Token Supply | B4: _ | C4: 10000000
A5: Token Price (initial) | B5: $ | C5: 10
A6: GP Share | B6: % | C6: 20
A7: Mgmt fee | B7: % | C7: 2
A8: LP Share | B8: % | C8: 80

Sheet Empirical Model
A2: S.No | C2: LP1 | D2: LP2 | E2: LP21 New LP | F2: LP3 | G2: LP4 | H2: LP5 | I2: LP6 | J2: LP7 | K2: LP8 | L2: LP9 | M2: LP10 | N2: LP11 | O2: LP12 | P2: LP13 | Q2: LP14 | R2: LP15 | S2: LP16 | T2: LP17 | U2: LP18 | V2: LP19 | W2: LP20
A3: LP Name | C3: BlackRock PE | D3: CalPERS Pension Fund | E3: Shivam | F3: Harvard Endowment | G3: Ontario Teachers | H3: GIC Singapore | I3: ADIA Abu Dhabi | J3: Yale Endowment | K3: CPP Investments | L3: Goldman Sachs AM | M3: Temasek Holdings | N3: Fidelity PE Fund | O3: TPG Capital | P3: Brookfield AM | Q3: Carlyle Group | R3: Morgan Stanley AIP | S3: Blackstone FoF | T3: KKR Fund of Funds | U3: Apollo Global | V3: Sovereign PE Fund (QIA) | W3: Family Office (Smith Capital)
A4: % Allocation | C4: 0.12 | D4: 0.1 | E4: Let’s say LP2 wants to exit early → sells 500,000 tokens at $13/token to New LP21. | F4: 0.08 | G4: 0.07 | H4: 0.06 | I4: 0.07 | J4: 0.05 | K4: 0.05 | L4: 0.05 | M4: 0.04 | N4: 0.04 | O4: 0.04 | P4: 0.03 | Q4: 0.03 | R4: 0.03 | S4: 0.02 | T4: 0.02 | U4: 0.02 | V4: 0.02 | W4: 0.02
A5: Commitment (Million) | B5: =SUM(C5:W5) -> 100000000 | C5: 12000000 | D5: 10000000 | F5: 9000000 | G5: 8000000 | H5: 8000000 | I5: 7000000 | J5: 5000000 | K5: 5000000 | L5: 5000000 | M5: 4000000 | N5: 4000000 | O5: 4000000 | P5: 3000000 | Q5: 3000000 | R5: 3000000 | S5: 2000000 | T5: 2000000 | U5: 2000000 | V5: 2000000 | W5: 2000000
A6: Tokens | B6: =SUM(C6:W6) -> 10000000 | C6: =C5/Assumptions!$C$5 -> 1200000 | D6: =D5/Assumptions!$C$5 -> 1000000 | F6: =F5/Assumptions!$C$5 -> 900000 | G6: =G5/Assumptions!$C$5 -> 800000 | H6: =H5/Assumptions!$C$5 -> 800000 | I6: =I5/Assumptions!$C$5 -> 700000 | J6: =J5/Assumptions!$C$5 -> 500000 | K6: =K5/Assumptions!$C$5 -> 500000 | L6: =L5/Assumptions!$C$5 -> 500000 | M6: =M5/Assumptions!$C$5 -> 400000 | ... W6: =W5/Assumptions!$C$5 -> 200000
A7: Mgmt Fees | B7: 0.02 | C7: =C5*$B$7 -> 240000 | D7: =D5*$B$7 -> 200000 | F7: =F5*$B$7 -> 180000 | G7: =G5*$B$7 -> 160000 | H7: =H5*$B$7 -> 160000 | I7: =I5*$B$7 -> 140000 | J7: =J5*$B$7 -> 100000 | K7: =K5*$B$7 -> 100000 | L7: =L5*$B$7 -> 100000 | M7: =M5*$B$7 -> 80000 | ... W7: =W5*$B$7 -> 40000
A9: % Allocation New | D9: 0.05 | E9: 0.05
A10: Commitment (Million) | E10: =B22*(D6/2) -> 6655000
A11: Tokens | D11: =D6/2 -> 500000 | E11: =D6/2 -> 500000
A12: Mgmt Fees | B12: 0.02
B14: NAV
A15: Y0 | B15: =SUM(C15:W15) -> 100000000 | C15: =C5 -> 12000000 | D15: =D5 -> 10000000 | F15: =F5 -> 9000000 | G15: =G5 -> 8000000 | H15: =H5 -> 8000000 | I15: =I5 -> 7000000 | J15: =J5 -> 5000000 | K15: =K5 -> 5000000 | L15: =L5 -> 5000000 | M15: =M5 -> 4000000 | ... W15: =W5 -> 2000000
A16: Token Value | B16: =B15/$B$6 -> 10 | C16: 0.1
A17: Y1 | B17: =SUM(C17:W17) -> 110000000 | C17: =($C$16*C15)+C15 -> 13200000 | D17: =($C$16*D15)+D15 -> 11000000 | F17: =($C$16*F15)+F15 -> 9900000 | G17: =($C$16*G15)+G15 -> 8800000 | H17: =($C$16*H15)+H15 -> 8800000 | I17: =($C$16*I15)+I15 -> 7700000 | J17: =($C$16*J15)+J15 -> 5500000 | K17: =($C$16*K15)+K15 -> 5500000 | L17: =($C$16*L15)+L15 -> 5500000 | M17: =($C$16*M15)+M15 -> 4400000 | ... W17: =($C$16*W15)+W15 -> 2200000
A18: Token Value | B18: =B17/$B$6 -> 11 | C18: 0.1
A19: Y2 | B19: =SUM(C19:W19) -> 121000000 | C19: =($C$16*C17)+C17 -> 14520000 | D19: =($C$16*D17)+D17 -> 12100000 | F19: =($C$16*F17)+F17 -> 10890000 | G19: =($C$16*G17)+G17 -> 9680000 | H19: =($C$16*H17)+H17 -> 9680000 | I19: =($C$16*I17)+I17 -> 8470000 | J19: =($C$16*J17)+J17 -> 6050000 | K19: =($C$16*K17)+K17 -> 6050000 | L19: =($C$16*L17)+L17 -> 6050000 | M19: =($C$16*M17)+M17 -> 4840000 | ... W19: =($C$16*W17)+W17 -> 2420000
A20: Token Value | B20: =B19/$B$6 -> 12.1 | C20: 0.1
A21: Y3 | B21: =SUM(C21:W21) -> 133100000 | C21: =($C$16*C19)+C19 -> 15972000 | D21: =($C$16*D19)+D19 -> 13310000 | F21: =($C$16*F19)+F19 -> 11979000 | G21: =($C$16*G19)+G19 -> 10648000 | H21: =($C$16*H19)+H19 -> 10648000 | I21: =($C$16*I19)+I19 -> 9317000 | J21: =($C$16*J19)+J19 -> 6655000 | K21: =($C$16*K19)+K19 -> 6655000 | L21: =($C$16*L19)+L19 -> 6655000 | M21: =($C$16*M19)+M19 -> 5324000 | ... W21: =($C$16*W19)+W19 -> 2662000
A22: Token Value | B22: =B21/$B$6 -> 13.31 | C22: 0.1
A23: Y4 | B23: =SUM(C23:W23) -> 146410000 | C23: =($C$16*C21)+C21 -> 17569200 | D23: =($C$16*D21)+D21-E10 -> 7986000 | E23: =E10 -> 6655000 | F23: =($C$16*F21)+F21 -> 13176900 | G23: =($C$16*G21)+G21 -> 11712800 | H23: =($C$16*H21)+H21 -> 11712800 | I23: =($C$16*I21)+I21 -> 10248700 | J23: =($C$16*J21)+J21 -> 7320500 | K23: =($C$16*K21)+K21 -> 7320500 | L23: =($C$16*L21)+L21 -> 7320500 | M23: =($C$16*M21)+M21 -> 5856400 | ... W23: =($C$16*W21)+W21 -> 2928200
A24: Token Value | B24: =B23/$B$6 -> 14.641 | C24: 0.1
A25: Y5 | B25: =SUM(C25:W25) -> 161051000 | C25: =($C$16*C23)+C23 -> 19326120 | D25: =($C$16*D23)+D23 -> 8784600 | E25: =($C$16*E23)+E23 -> 7320500 | F25: =($C$16*F23)+F23 -> 14494590 | G25: =($C$16*G23)+G23 -> 12884080 | H25: =($C$16*H23)+H23 -> 12884080 | I25: =($C$16*I23)+I23 -> 11273570 | J25: =($C$16*J23)+J23 -> 8052550 | ... W25: =($C$16*W23)+W23 -> 3221020
A26: Token Value | B26: =B25/$B$6 -> 16.1051 | C26: 0.1
A27: Y6 | B27: =SUM(C27:W27) -> 177156100 | C27: =($C$16*C25)+C25 -> 21258732 | D27: =($C$16*D25)+D25 -> 9663060 | E27: =($C$16*E25)+E25 -> 8052550 | F27: =($C$16*F25)+F25 -> 15944049 | G27: =($C$16*G25)+G25 -> 14172488 | H27: =($C$16*H25)+H25 -> 14172488 | I27: =($C$16*I25)+I25 -> 12400927 | J27: =($C$16*J25)+J25 -> 8857805 | ... W27: =($C$16*W25)+W25 -> 3543122
A28: Token Value | B28: =B27/$B$6 -> 17.71561 | C28: 0.1
A29: Y7 | B29: =SUM(C29:W29) -> 194871710 | C29: =($C$16*C27)+C27 -> 23384605 | D29: =($C$16*D27)+D27 -> 10629366 | E29: =($C$16*E27)+E27 -> 8857805 | F29: =($C$16*F27)+F27 -> 17538454 | G29: =($C$16*G27)+G27 -> 15589737 | H29: =($C$16*H27)+H27 -> 15589737 | I29: =($C$16*I27)+I27 -> 13641020 | J29: =($C$16*J27)+J27 -> 9743585.5 | ... W29: =($C$16*W27)+W27 -> 3897434.2
B30: =B29/$B$6 -> 19.487171
A32: Profit | B32: =SUM(C32:W32) -> 94871710 | C32: =C29-C15 -> 11384605 | D32: =D29-D15 -> 629366 | E32: =E29-E15 -> 8857805 | F32: =F29-F15 -> 8538453.9 | G32: =G29-G15 -> 7589736.8 | H32: =H29-H15 -> 7589736.8 | I32: =I29-I15 -> 6641019.7 | J32: =J29-J15 -> 4743585.5 | ... W32: =W29-W15 -> 1897434.2
A33: GP (20%) | C33: =C32*20% -> 2276921 | D33: =D32*20% -> 125873.2 | E33: =E32*20% -> 1771561 | F33: =F32*20% -> 1707690.8 | G33: =G32*20% -> 1517947.4 | H33: =H32*20% -> 1517947.4 | I33: =I32*20% -> 1328203.9 | J33: =J32*20% -> 948717.1 | ... W33: =W32*20% -> 379486.84
A34: Net profit | B34: =SUM(C34:W34) -> 73897368 | C34: =C32-C7-C33 -> 8867684.2 | D34: =D32-D7-D33 -> 303492.8 | E34: =E32-E7-E33 -> 7086244 | F34: =F32-F7-F33 -> 6650763.1 | G34: =G32-G7-G33 -> 5911789.4 | H34: =H32-H7-H33 -> 5911789.4 | I34: =I32-I7-I33 -> 5172815.8 | J34: =J32-J7-J33 -> 3694868.4 | ... W34: =W32-W7-W33 -> 1477947.4
